Metadata-Version: 2.1
Name: micropython-sgp40
Version: 0.1.0
Summary: MicroPython I2C driver for Sensirion SGP40 VOC sensor
Home-page: https://github.com/agners/micropython-sgp40
Author: Stefan Agner
Author-email: stefan@agner.ch
Maintainer: Stefan Agner
Maintainer-email: stefan@agner.ch
License: MIT
Keywords: sgp40,voc,micropython,i2c
Platform: UNKNOWN
Classifier: Development Status :: 4 - Beta
Classifier: Programming Language :: Python :: Implementation :: MicroPython
Classifier: License :: OSI Approved :: MIT License
